vertibit_osi_image_generator/__init__.py
vertibit_osi_image_generator/cli.py
vertibit_osi_image_generator/config/config.json
vertibit_osi_image_generator/config/docker-ignore/nodejs/.dockerignore
vertibit_osi_image_generator/config/docker-ignore/python/.dockerignore
vertibit_osi_image_generator/image_build/__init__.py
vertibit_osi_image_generator/image_build/generate_docker_image.py
vertibit_osi_image_generator/main/__init__.py
vertibit_osi_image_generator/main/config_file_processor.py
vertibit_osi_image_generator/main/docker_file_generation.py
vertibit_osi_image_generator/main/language_scanner.py
vertibit_osi_image_generator/nodejs/__init__.py
vertibit_osi_image_generator/nodejs/docker_file_generation.py
vertibit_osi_image_generator/nodejs/docker_file_generation_prep.py
vertibit_osi_image_generator/nodejs/nodejs_config.py
vertibit_osi_image_generator/python/__init__.py
vertibit_osi_image_generator/python/docker_file_generation.py
vertibit_osi_image_generator/python/docker_file_generation_prep.py
vertibit_osi_image_generator/python/python_config.py
vertibit_osi_image_generator/shared_aux/__init__.py
vertibit_osi_image_generator/shared_aux/comand_runner.py
vertibit_osi_image_generator/shared_aux/config_aux.py
vertibit_osi_image_generator/shared_aux/extract_and_run_image.py
vertibit_osi_image_generator/shared_aux/file_scanner_shared.py
vertibit_osi_image_generator/shared_aux/language_package_manager_scanner.py
vertibit_osi_image_generator/shared_aux/language_package_managers.py
vertibit_osi_image_generator/shared_aux/shared.py
vertibit_osi_image_generator/testing/__init__.py
vertibit_osi_image_generator/testing/checkov.py
vertibit_osi_image_generator/verti_file_config_aux/__init__.py
vertibit_osi_image_generator/verti_file_config_aux/file_config.py
verti_osi-2.5.2.dist-info/METADATA
verti_osi-2.5.2.dist-info/WHEEL
verti_osi-2.5.2.dist-info/entry_points.txt
verti_osi-2.5.2.dist-info/top_level.txt
verti_osi-2.5.2.dist-info/RECORD
