Metadata-Version: 2.4
Name: verti-osi
Version: 2.5.2
Summary: A CLI tool for generating OCI-compliant container images for Python and Node.js projects.
Home-page: https://github.com/vtb-wanderers63/py-logging-module
Author: VTB Wanderer DG
Author-email: vtb.wanderers63@gmail.com
Requires-Python: >=3.7
Requires-Dist: typer
Requires-Dist: pyyaml
Requires-Dist: jsonschema
Requires-Dist: checkov
Dynamic: author
Dynamic: author-email
Dynamic: home-page
Dynamic: requires-python
